camb/HighLExtrapTemplate_lenspotentialCls.dat
camb/PArthENoPE_880.2_marcucci.dat
camb/PArthENoPE_880.2_standard.dat
camb/PRIMAT_Yp_DH_Error.dat
camb/PRIMAT_Yp_DH_ErrorMC_2021.dat
camb/PRIMAT_Yp_DH_ErrorMC_2024.dat
camb/__init__.py
camb/_command_line.py
camb/_compilers.py
camb/_config.py
camb/baseconfig.py
camb/bbn.py
camb/bispectrum.py
camb/camb.py
camb/cambdll.dll
camb/constants.py
camb/correlations.py
camb/dark_energy.py
camb/emission_angle.py
camb/initialpower.py
camb/mathutils.py
camb/model.py
camb/nonlinear.py
camb/postborn.py
camb/recombination.py
camb/reionization.py
camb/results.py
camb/sources.py
camb/symbolic.py
camb/tests/__init__.py
camb/tests/camb_test.py
camb/tests/hmcode_test.py
camb-1.6.5.dist-info/licenses/LICENCE.txt
camb-1.6.5.dist-info/METADATA
camb-1.6.5.dist-info/WHEEL
camb-1.6.5.dist-info/entry_points.txt
camb-1.6.5.dist-info/top_level.txt
camb-1.6.5.dist-info/RECORD
