Metadata-Version: 2.4
Name: camb
Version: 1.6.5
Summary: Code for Anisotropies in the Microwave Background
Author: Antony Lewis
License-Expression: LicenseRef-LGPLv3-arxiv
Project-URL: Homepage, https://camb.info
Project-URL: Documentation, https://camb.readthedocs.io
Project-URL: Source, https://github.com/cmbant/camb
Project-URL: Tracker, https://github.com/cmbant/camb/issues
Project-URL: Licensing, https://github.com/cmbant/camb/blob/master/LICENCE.txt
Keywords: cosmology,CAMB,CMB
Platform: any
Classifier: Development Status :: 5 - Production/Stable
Classifier: Operating System :: OS Independent
Classifier: Environment :: Console
Classifier: Intended Audience :: Science/Research
Classifier: Topic :: Scientific/Engineering :: Astronomy
Classifier: Programming Language :: Python :: 3.10
Classifier: Programming Language :: Python :: 3.11
Classifier: Programming Language :: Python :: 3.12
Classifier: Programming Language :: Python :: 3.13
Classifier: Programming Language :: Python :: 3.14
Requires-Python: >=3.10.0
License-File: LICENCE.txt
Requires-Dist: numpy>=1.22
Requires-Dist: scipy>=1.0
Requires-Dist: sympy>=1.0
Requires-Dist: packaging>=24.2
Provides-Extra: docs
Requires-Dist: sphinx>=4.0; extra == "docs"
Requires-Dist: sphinx_rtd_theme>=1.0; extra == "docs"
Requires-Dist: sphinxcontrib-jquery; extra == "docs"
Requires-Dist: sphinx_markdown_builder; extra == "docs"
Requires-Dist: jupytext; extra == "docs"
Provides-Extra: dev
Requires-Dist: ruff>=0.11.0; extra == "dev"
Requires-Dist: pre-commit>=3.0.0; extra == "dev"
Dynamic: license-file
Dynamic: platform
